directory_healthcheck/__init__.py
directory_healthcheck/apps.py
directory_healthcheck/backends.py
directory_healthcheck/views.py
directory_healthcheck/templates/directory_healthcheck/healthcheck.html
directory_healthcheck/templates/directory_healthcheck/pingdom.xml
directory_healthcheck-3.8.dist-info/licenses/LICENSE
directory_healthcheck-3.8.dist-info/METADATA
directory_healthcheck-3.8.dist-info/WHEEL
directory_healthcheck-3.8.dist-info/top_level.txt
directory_healthcheck-3.8.dist-info/RECORD
