Metadata-Version: 2.4
Name: directory_healthcheck
Version: 3.8
Summary: Library to streamline healthchecks for Directory apps.
Home-page: https://github.com/uktrade/directory-healthcheck
Author: Department for International Trade
License: MIT
Classifier: Development Status :: 5 - Production/Stable
Classifier: Environment :: Web Environment
Classifier: Framework :: Django
Classifier: Framework :: Django :: 1.11
Classifier: Framework :: Django :: 2.0
Classifier: Framework :: Django :: 2.1
Classifier: Framework :: Django :: 2.2
Classifier: Framework :: Django :: 3.1
Classifier: Framework :: Django :: 3.2
Classifier: Framework :: Django :: 4.1
Classifier: Framework :: Django :: 4.2
Classifier: Intended Audience :: Developers
Classifier: License :: OSI Approved :: MIT License
Classifier: Natural Language :: English
Classifier: Programming Language :: Python :: 3.9
Classifier: Programming Language :: Python :: 3.13
Classifier: Operating System :: OS Independent
Classifier: Topic :: Software Development :: Libraries :: Python Modules
License-File: LICENSE
Requires-Dist: django-health-check==3.18.2
Requires-Dist: django<5.0,>=4.2.10
Provides-Extra: test
Requires-Dist: pytest>=4.6.0; extra == "test"
Requires-Dist: pytest-cov>=2.11.0; extra == "test"
Requires-Dist: pytest-django==4.8.0; extra == "test"
Requires-Dist: flake8==5.0.4; extra == "test"
Requires-Dist: codecov>=2.0.16; extra == "test"
Requires-Dist: twine; extra == "test"
Requires-Dist: wheel<1.0.0,>=0.31.0; extra == "test"
Requires-Dist: raven==5.19.0; extra == "test"
Requires-Dist: setuptools; extra == "test"
Requires-Dist: directory-sso-api-client; extra == "test"
Requires-Dist: directory-api-client; extra == "test"
Requires-Dist: directory-forms-api-client; extra == "test"
Requires-Dist: directory-cms-client; extra == "test"
Requires-Dist: directory-client-core; extra == "test"
Dynamic: author
Dynamic: classifier
Dynamic: description
Dynamic: description-content-type
Dynamic: home-page
Dynamic: license
Dynamic: license-file
Dynamic: provides-extra
Dynamic: requires-dist
Dynamic: summary
